fanfare/__init__.py
fanfare-0.1.0.dist-info/LICENSE
fanfare-0.1.0.dist-info/METADATA
fanfare-0.1.0.dist-info/WHEEL
fanfare-0.1.0.dist-info/top_level.txt
fanfare-0.1.0.dist-info/RECORD
